{"nodes": [{"id": "users_nmiller_documents_github_aortica_aortica_integration_worklist_py", "label": "worklist.py", "file_type": "code", "source_file": "aortica/integration/worklist.py", "source_location": "L1"}, {"id": "integration_worklist_urgencyrules", "label": "UrgencyRules", "file_type": "code", "source_file": "aortica/integration/worklist.py", "source_location": "L205"}, {"id": "integration_worklist_worklistitem", "label": "WorklistItem", "file_type": "code", "source_file": "aortica/integration/worklist.py", "source_location": "L240"}, {"id": "integration_worklist_worklistitem_to_dict", "label": ".to_dict()", "file_type": "code", "source_file": "aortica/integration/worklist.py", "source_location": "L262"}, {"id": "any", "label": "Any", "file_type": "code", "source_file": "", "source_location": ""}, {"id": "integration_worklist_prioritizedworklist", "label": "PrioritizedWorklist", "file_type": "code", "source_file": "aortica/integration/worklist.py", "source_location": "L276"}, {"id": "integration_worklist_prioritizedworklist_to_dict", "label": ".to_dict()", "file_type": "code", "source_file": "aortica/integration/worklist.py", "source_location": "L295"}, {"id": "integration_worklist_get_task_predictions", "label": "_get_task_predictions()", "file_type": "code", "source_file": "aortica/integration/worklist.py", "source_location": "L311"}, {"id": "integration_worklist_extract_predictions", "label": "_extract_predictions()", "file_type": "code", "source_file": "aortica/integration/worklist.py", "source_location": "L321"}, {"id": "integration_worklist_load_urgency_rules", "label": "load_urgency_rules()", "file_type": "code", "source_file": "aortica/integration/worklist.py", "source_location": "L384"}, {"id": "path", "label": "Path", "file_type": "code", "source_file": "", "source_location": ""}, {"id": "integration_worklist_worklistprioritizer", "label": "WorklistPrioritizer", "file_type": "code", "source_file": "aortica/integration/worklist.py", "source_location": "L445"}, {"id": "integration_worklist_worklistprioritizer_init", "label": ".__init__()", "file_type": "code", "source_file": "aortica/integration/worklist.py", "source_location": "L466"}, {"id": "integration_worklist_worklistprioritizer_score_single", "label": "._score_single()", "file_type": "code", "source_file": "aortica/integration/worklist.py", "source_location": "L478"}, {"id": "integration_worklist_worklistprioritizer_compute_score", "label": "._compute_score()", "file_type": "code", "source_file": "aortica/integration/worklist.py", "source_location": "L585"}, {"id": "integration_worklist_worklistprioritizer_prioritize", "label": ".prioritize()", "file_type": "code", "source_file": "aortica/integration/worklist.py", "source_location": "L632"}, {"id": "integration_worklist_rationale_1", "label": "AI-driven Worklist Prioritization Module.  Provides :class:`WorklistPrioritizer`", "file_type": "rationale", "source_file": "aortica/integration/worklist.py", "source_location": "L1"}, {"id": "integration_worklist_rationale_206", "label": "Configurable urgency rules for worklist prioritization.      Attributes:", "file_type": "rationale", "source_file": "aortica/integration/worklist.py", "source_location": "L206"}, {"id": "integration_worklist_rationale_241", "label": "A single ECG entry in the prioritized worklist.      Attributes:         ecg_id:", "file_type": "rationale", "source_file": "aortica/integration/worklist.py", "source_location": "L241"}, {"id": "integration_worklist_rationale_263", "label": "Serialise as a plain dictionary.", "file_type": "rationale", "source_file": "aortica/integration/worklist.py", "source_location": "L263"}, {"id": "integration_worklist_rationale_277", "label": "A prioritized list of ECGs sorted by clinical urgency.      Attributes:", "file_type": "rationale", "source_file": "aortica/integration/worklist.py", "source_location": "L277"}, {"id": "integration_worklist_rationale_296", "label": "Serialise as a plain dictionary.", "file_type": "rationale", "source_file": "aortica/integration/worklist.py", "source_location": "L296"}, {"id": "integration_worklist_rationale_312", "label": "Extract predictions for a single task from a multi-task output.      Handles bot", "file_type": "rationale", "source_file": "aortica/integration/worklist.py", "source_location": "L312"}, {"id": "integration_worklist_rationale_324", "label": "Extract per-class confidence values from a MultiTaskOutput-like object.      Sup", "file_type": "rationale", "source_file": "aortica/integration/worklist.py", "source_location": "L324"}, {"id": "integration_worklist_rationale_385", "label": "Load urgency rules from a YAML file.      The YAML file should have keys matchin", "file_type": "rationale", "source_file": "aortica/integration/worklist.py", "source_location": "L385"}, {"id": "integration_worklist_rationale_446", "label": "AI-driven worklist prioritizer sorting ECGs by clinical urgency.      The priori", "file_type": "rationale", "source_file": "aortica/integration/worklist.py", "source_location": "L446"}, {"id": "integration_worklist_rationale_482", "label": "Score a single ECG's urgency.          Returns:             (urgency_score, urge", "file_type": "rationale", "source_file": "aortica/integration/worklist.py", "source_location": "L482"}, {"id": "integration_worklist_rationale_590", "label": "Compute the 0\u2013100 urgency score.          Score bands:             critical: 80\u2013", "file_type": "rationale", "source_file": "aortica/integration/worklist.py", "source_location": "L590"}, {"id": "integration_worklist_rationale_637", "label": "Prioritize a list of multi-task ECG results by urgency.          Args:", "file_type": "rationale", "source_file": "aortica/integration/worklist.py", "source_location": "L637"}], "edges": [{"source": "users_nmiller_documents_github_aortica_aortica_integration_worklist_py", "target": "os", "relation": "imports", "context": "import", "confidence": "EXTRACTED", "source_file": "aortica/integration/worklist.py", "source_location": "L33", "weight": 1.0}, {"source": "users_nmiller_documents_github_aortica_aortica_integration_worklist_py", "target": "dataclasses", "relation": "imports_from", "context": "import", "confidence": "EXTRACTED", "source_file": "aortica/integration/worklist.py", "source_location": "L34", "weight": 1.0}, {"source": "users_nmiller_documents_github_aortica_aortica_integration_worklist_py", "target": "pathlib", "relation": "imports_from", "context": "import", "confidence": "EXTRACTED", "source_file": "aortica/integration/worklist.py", "source_location": "L35", "weight": 1.0}, {"source": "users_nmiller_documents_github_aortica_aortica_integration_worklist_py", "target": "typing", "relation": "imports_from", "context": "import", "confidence": "EXTRACTED", "source_file": "aortica/integration/worklist.py", "source_location": "L36", "weight": 1.0}, {"source": "users_nmiller_documents_github_aortica_aortica_integration_worklist_py", "target": "yaml", "relation": "imports", "context": "import", "confidence": "EXTRACTED", "source_file": "aortica/integration/worklist.py", "source_location": "L39", "weight": 1.0}, {"source": "users_nmiller_documents_github_aortica_aortica_integration_worklist_py", "target": "integration_worklist_urgencyrules", "relation": "contains", "confidence": "EXTRACTED", "source_file": "aortica/integration/worklist.py", "source_location": "L205", "weight": 1.0}, {"source": "users_nmiller_documents_github_aortica_aortica_integration_worklist_py", "target": "integration_worklist_worklistitem", "relation": "contains", "confidence": "EXTRACTED", "source_file": "aortica/integration/worklist.py", "source_location": "L240", "weight": 1.0}, {"source": "integration_worklist_worklistitem", "target": "integration_worklist_worklistitem_to_dict", "relation": "method", "confidence": "EXTRACTED", "source_file": "aortica/integration/worklist.py", "source_location": "L262", "weight": 1.0}, {"source": "integration_worklist_worklistitem_to_dict", "target": "any", "relation": "references", "context": "generic_arg", "confidence": "EXTRACTED", "source_file": "aortica/integration/worklist.py", "source_location": "L262", "weight": 1.0}, {"source": "users_nmiller_documents_github_aortica_aortica_integration_worklist_py", "target": "integration_worklist_prioritizedworklist", "relation": "contains", "confidence": "EXTRACTED", "source_file": "aortica/integration/worklist.py", "source_location": "L276", "weight": 1.0}, {"source": "integration_worklist_prioritizedworklist", "target": "integration_worklist_prioritizedworklist_to_dict", "relation": "method", "confidence": "EXTRACTED", "source_file": "aortica/integration/worklist.py", "source_location": "L295", "weight": 1.0}, {"source": "integration_worklist_prioritizedworklist_to_dict", "target": "any", "relation": "references", "context": "generic_arg", "confidence": "EXTRACTED", "source_file": "aortica/integration/worklist.py", "source_location": "L295", "weight": 1.0}, {"source": "users_nmiller_documents_github_aortica_aortica_integration_worklist_py", "target": "integration_worklist_get_task_predictions", "relation": "contains", "confidence": "EXTRACTED", "source_file": "aortica/integration/worklist.py", "source_location": "L311", "weight": 1.0}, {"source": "integration_worklist_get_task_predictions", "target": "any", "relation": "references", "context": "parameter_type", "confidence": "EXTRACTED", "source_file": "aortica/integration/worklist.py", "source_location": "L311", "weight": 1.0}, {"source": "integration_worklist_get_task_predictions", "target": "any", "relation": "references", "context": "return_type", "confidence": "EXTRACTED", "source_file": "aortica/integration/worklist.py", "source_location": "L311", "weight": 1.0}, {"source": "users_nmiller_documents_github_aortica_aortica_integration_worklist_py", "target": "integration_worklist_extract_predictions", "relation": "contains", "confidence": "EXTRACTED", "source_file": "aortica/integration/worklist.py", "source_location": "L321", "weight": 1.0}, {"source": "integration_worklist_extract_predictions", "target": "any", "relation": "references", "context": "parameter_type", "confidence": "EXTRACTED", "source_file": "aortica/integration/worklist.py", "source_location": "L321", "weight": 1.0}, {"source": "users_nmiller_documents_github_aortica_aortica_integration_worklist_py", "target": "integration_worklist_load_urgency_rules", "relation": "contains", "confidence": "EXTRACTED", "source_file": "aortica/integration/worklist.py", "source_location": "L384", "weight": 1.0}, {"source": "integration_worklist_load_urgency_rules", "target": "path", "relation": "references", "context": "parameter_type", "confidence": "EXTRACTED", "source_file": "aortica/integration/worklist.py", "source_location": "L384", "weight": 1.0}, {"source": "integration_worklist_load_urgency_rules", "target": "integration_worklist_urgencyrules", "relation": "references", "context": "return_type", "confidence": "EXTRACTED", "source_file": "aortica/integration/worklist.py", "source_location": "L384", "weight": 1.0}, {"source": "users_nmiller_documents_github_aortica_aortica_integration_worklist_py", "target": "integration_worklist_worklistprioritizer", "relation": "contains", "confidence": "EXTRACTED", "source_file": "aortica/integration/worklist.py", "source_location": "L445", "weight": 1.0}, {"source": "integration_worklist_worklistprioritizer", "target": "integration_worklist_worklistprioritizer_init", "relation": "method", "confidence": "EXTRACTED", "source_file": "aortica/integration/worklist.py", "source_location": "L466", "weight": 1.0}, {"source": "integration_worklist_worklistprioritizer_init", "target": "integration_worklist_urgencyrules", "relation": "references", "context": "generic_arg", "confidence": "EXTRACTED", "source_file": "aortica/integration/worklist.py", "source_location": "L466", "weight": 1.0}, {"source": "integration_worklist_worklistprioritizer_init", "target": "path", "relation": "references", "context": "generic_arg", "confidence": "EXTRACTED", "source_file": "aortica/integration/worklist.py", "source_location": "L466", "weight": 1.0}, {"source": "integration_worklist_worklistprioritizer", "target": "integration_worklist_worklistprioritizer_score_single", "relation": "method", "confidence": "EXTRACTED", "source_file": "aortica/integration/worklist.py", "source_location": "L478", "weight": 1.0}, {"source": "integration_worklist_worklistprioritizer_score_single", "target": "any", "relation": "references", "context": "generic_arg", "confidence": "EXTRACTED", "source_file": "aortica/integration/worklist.py", "source_location": "L478", "weight": 1.0}, {"source": "integration_worklist_worklistprioritizer", "target": "integration_worklist_worklistprioritizer_compute_score", "relation": "method", "confidence": "EXTRACTED", "source_file": "aortica/integration/worklist.py", "source_location": "L585", "weight": 1.0}, {"source": "integration_worklist_worklistprioritizer_compute_score", "target": "any", "relation": "references", "context": "generic_arg", "confidence": "EXTRACTED", "source_file": "aortica/integration/worklist.py", "source_location": "L585", "weight": 1.0}, {"source": "integration_worklist_worklistprioritizer", "target": "integration_worklist_worklistprioritizer_prioritize", "relation": "method", "confidence": "EXTRACTED", "source_file": "aortica/integration/worklist.py", "source_location": "L632", "weight": 1.0}, {"source": "integration_worklist_worklistprioritizer_prioritize", "target": "any", "relation": "references", "context": "generic_arg", "confidence": "EXTRACTED", "source_file": "aortica/integration/worklist.py", "source_location": "L632", "weight": 1.0}, {"source": "integration_worklist_worklistprioritizer_prioritize", "target": "integration_worklist_prioritizedworklist", "relation": "references", "context": "return_type", "confidence": "EXTRACTED", "source_file": "aortica/integration/worklist.py", "source_location": "L632", "weight": 1.0}, {"source": "integration_worklist_extract_predictions", "target": "integration_worklist_get_task_predictions", "relation": "calls", "context": "call", "confidence": "EXTRACTED", "source_file": "aortica/integration/worklist.py", "source_location": "L344", "weight": 1.0}, {"source": "integration_worklist_load_urgency_rules", "target": "path", "relation": "calls", "context": "call", "confidence": "EXTRACTED", "source_file": "aortica/integration/worklist.py", "source_location": "L408", "weight": 1.0}, {"source": "integration_worklist_load_urgency_rules", "target": "integration_worklist_urgencyrules", "relation": "calls", "context": "call", "confidence": "EXTRACTED", "source_file": "aortica/integration/worklist.py", "source_location": "L415", "weight": 1.0}, {"source": "integration_worklist_worklistprioritizer_init", "target": "integration_worklist_load_urgency_rules", "relation": "calls", "context": "call", "confidence": "EXTRACTED", "source_file": "aortica/integration/worklist.py", "source_location": "L474", "weight": 1.0}, {"source": "integration_worklist_worklistprioritizer_init", "target": "integration_worklist_urgencyrules", "relation": "calls", "context": "call", "confidence": "EXTRACTED", "source_file": "aortica/integration/worklist.py", "source_location": "L476", "weight": 1.0}, {"source": "integration_worklist_worklistprioritizer_score_single", "target": "integration_worklist_worklistprioritizer_compute_score", "relation": "calls", "context": "call", "confidence": "EXTRACTED", "source_file": "aortica/integration/worklist.py", "source_location": "L570", "weight": 1.0}, {"source": "integration_worklist_worklistprioritizer_prioritize", "target": "integration_worklist_extract_predictions", "relation": "calls", "context": "call", "confidence": "EXTRACTED", "source_file": "aortica/integration/worklist.py", "source_location": "L664", "weight": 1.0}, {"source": "integration_worklist_worklistprioritizer_prioritize", "target": "integration_worklist_worklistprioritizer_score_single", "relation": "calls", "context": "call", "confidence": "EXTRACTED", "source_file": "aortica/integration/worklist.py", "source_location": "L665", "weight": 1.0}, {"source": "integration_worklist_worklistprioritizer_prioritize", "target": "integration_worklist_worklistitem", "relation": "calls", "context": "call", "confidence": "EXTRACTED", "source_file": "aortica/integration/worklist.py", "source_location": "L684", "weight": 1.0}, {"source": "integration_worklist_worklistprioritizer_prioritize", "target": "integration_worklist_prioritizedworklist", "relation": "calls", "context": "call", "confidence": "EXTRACTED", "source_file": "aortica/integration/worklist.py", "source_location": "L703", "weight": 1.0}, {"source": "integration_worklist_rationale_1", "target": "users_nmiller_documents_github_aortica_aortica_integration_worklist_py", "relation": "rationale_for", "confidence": "EXTRACTED", "source_file": "aortica/integration/worklist.py", "source_location": "L1", "weight": 1.0}, {"source": "integration_worklist_rationale_206", "target": "integration_worklist_urgencyrules", "relation": "rationale_for", "confidence": "EXTRACTED", "source_file": "aortica/integration/worklist.py", "source_location": "L206", "weight": 1.0}, {"source": "integration_worklist_rationale_241", "target": "integration_worklist_worklistitem", "relation": "rationale_for", "confidence": "EXTRACTED", "source_file": "aortica/integration/worklist.py", "source_location": "L241", "weight": 1.0}, {"source": "integration_worklist_rationale_263", "target": "integration_worklist_worklistitem_to_dict", "relation": "rationale_for", "confidence": "EXTRACTED", "source_file": "aortica/integration/worklist.py", "source_location": "L263", "weight": 1.0}, {"source": "integration_worklist_rationale_277", "target": "integration_worklist_prioritizedworklist", "relation": "rationale_for", "confidence": "EXTRACTED", "source_file": "aortica/integration/worklist.py", "source_location": "L277", "weight": 1.0}, {"source": "integration_worklist_rationale_296", "target": "integration_worklist_prioritizedworklist_to_dict", "relation": "rationale_for", "confidence": "EXTRACTED", "source_file": "aortica/integration/worklist.py", "source_location": "L296", "weight": 1.0}, {"source": "integration_worklist_rationale_312", "target": "integration_worklist_get_task_predictions", "relation": "rationale_for", "confidence": "EXTRACTED", "source_file": "aortica/integration/worklist.py", "source_location": "L312", "weight": 1.0}, {"source": "integration_worklist_rationale_324", "target": "integration_worklist_extract_predictions", "relation": "rationale_for", "confidence": "EXTRACTED", "source_file": "aortica/integration/worklist.py", "source_location": "L324", "weight": 1.0}, {"source": "integration_worklist_rationale_385", "target": "integration_worklist_load_urgency_rules", "relation": "rationale_for", "confidence": "EXTRACTED", "source_file": "aortica/integration/worklist.py", "source_location": "L385", "weight": 1.0}, {"source": "integration_worklist_rationale_446", "target": "integration_worklist_worklistprioritizer", "relation": "rationale_for", "confidence": "EXTRACTED", "source_file": "aortica/integration/worklist.py", "source_location": "L446", "weight": 1.0}, {"source": "integration_worklist_rationale_482", "target": "integration_worklist_worklistprioritizer_score_single", "relation": "rationale_for", "confidence": "EXTRACTED", "source_file": "aortica/integration/worklist.py", "source_location": "L482", "weight": 1.0}, {"source": "integration_worklist_rationale_590", "target": "integration_worklist_worklistprioritizer_compute_score", "relation": "rationale_for", "confidence": "EXTRACTED", "source_file": "aortica/integration/worklist.py", "source_location": "L590", "weight": 1.0}, {"source": "integration_worklist_rationale_637", "target": "integration_worklist_worklistprioritizer_prioritize", "relation": "rationale_for", "confidence": "EXTRACTED", "source_file": "aortica/integration/worklist.py", "source_location": "L637", "weight": 1.0}], "raw_calls": [{"caller_nid": "integration_worklist_get_task_predictions", "callee": "get", "is_member_call": true, "source_file": "/Users/nmiller/Documents/GitHub/aortica/aortica/integration/worklist.py", "source_location": "L317", "receiver": "output"}, {"caller_nid": "integration_worklist_extract_predictions", "callee": "items", "is_member_call": true, "source_file": "/Users/nmiller/Documents/GitHub/aortica/aortica/integration/worklist.py", "source_location": "L343", "receiver": "task_class_lists"}, {"caller_nid": "integration_worklist_extract_predictions", "callee": "items", "is_member_call": true, "source_file": "/Users/nmiller/Documents/GitHub/aortica/aortica/integration/worklist.py", "source_location": "L351", "receiver": "preds"}, {"caller_nid": "integration_worklist_extract_predictions", "callee": "tolist", "is_member_call": true, "source_file": "/Users/nmiller/Documents/GitHub/aortica/aortica/integration/worklist.py", "source_location": "L359", "receiver": null}, {"caller_nid": "integration_worklist_extract_predictions", "callee": "squeeze", "is_member_call": true, "source_file": "/Users/nmiller/Documents/GitHub/aortica/aortica/integration/worklist.py", "source_location": "L359", "receiver": null}, {"caller_nid": "integration_worklist_extract_predictions", "callee": "cpu", "is_member_call": true, "source_file": "/Users/nmiller/Documents/GitHub/aortica/aortica/integration/worklist.py", "source_location": "L359", "receiver": null}, {"caller_nid": "integration_worklist_extract_predictions", "callee": "detach", "is_member_call": true, "source_file": "/Users/nmiller/Documents/GitHub/aortica/aortica/integration/worklist.py", "source_location": "L359", "receiver": "preds"}, {"caller_nid": "integration_worklist_extract_predictions", "callee": "tolist", "is_member_call": true, "source_file": "/Users/nmiller/Documents/GitHub/aortica/aortica/integration/worklist.py", "source_location": "L361", "receiver": null}, {"caller_nid": "integration_worklist_extract_predictions", "callee": "squeeze", "is_member_call": true, "source_file": "/Users/nmiller/Documents/GitHub/aortica/aortica/integration/worklist.py", "source_location": "L361", "receiver": "preds"}, {"caller_nid": "integration_worklist_load_urgency_rules", "callee": "ImportError", "is_member_call": false, "source_file": "/Users/nmiller/Documents/GitHub/aortica/aortica/integration/worklist.py", "source_location": "L403", "receiver": null}, {"caller_nid": "integration_worklist_load_urgency_rules", "callee": "is_file", "is_member_call": true, "source_file": "/Users/nmiller/Documents/GitHub/aortica/aortica/integration/worklist.py", "source_location": "L409", "receiver": "path"}, {"caller_nid": "integration_worklist_load_urgency_rules", "callee": "FileNotFoundError", "is_member_call": false, "source_file": "/Users/nmiller/Documents/GitHub/aortica/aortica/integration/worklist.py", "source_location": "L410", "receiver": null}, {"caller_nid": "integration_worklist_load_urgency_rules", "callee": "safe_load", "is_member_call": true, "source_file": "/Users/nmiller/Documents/GitHub/aortica/aortica/integration/worklist.py", "source_location": "L413", "receiver": "yaml"}, {"caller_nid": "integration_worklist_load_urgency_rules", "callee": "items", "is_member_call": true, "source_file": "/Users/nmiller/Documents/GitHub/aortica/aortica/integration/worklist.py", "source_location": "L418", "receiver": null}, {"caller_nid": "integration_worklist_load_urgency_rules", "callee": "items", "is_member_call": true, "source_file": "/Users/nmiller/Documents/GitHub/aortica/aortica/integration/worklist.py", "source_location": "L422", "receiver": null}, {"caller_nid": "integration_worklist_load_urgency_rules", "callee": "items", "is_member_call": true, "source_file": "/Users/nmiller/Documents/GitHub/aortica/aortica/integration/worklist.py", "source_location": "L426", "receiver": null}, {"caller_nid": "integration_worklist_load_urgency_rules", "callee": "items", "is_member_call": true, "source_file": "/Users/nmiller/Documents/GitHub/aortica/aortica/integration/worklist.py", "source_location": "L430", "receiver": null}, {"caller_nid": "integration_worklist_load_urgency_rules", "callee": "items", "is_member_call": true, "source_file": "/Users/nmiller/Documents/GitHub/aortica/aortica/integration/worklist.py", "source_location": "L432", "receiver": "v"}, {"caller_nid": "integration_worklist_load_urgency_rules", "callee": "items", "is_member_call": true, "source_file": "/Users/nmiller/Documents/GitHub/aortica/aortica/integration/worklist.py", "source_location": "L435", "receiver": null}, {"caller_nid": "integration_worklist_worklistprioritizer_score_single", "callee": "get", "is_member_call": true, "source_file": "/Users/nmiller/Documents/GitHub/aortica/aortica/integration/worklist.py", "source_location": "L492", "receiver": "predictions"}, {"caller_nid": "integration_worklist_worklistprioritizer_score_single", "callee": "items", "is_member_call": true, "source_file": "/Users/nmiller/Documents/GitHub/aortica/aortica/integration/worklist.py", "source_location": "L493", "receiver": "task_preds"}, {"caller_nid": "integration_worklist_worklistprioritizer_score_single", "callee": "append", "is_member_call": true, "source_file": "/Users/nmiller/Documents/GitHub/aortica/aortica/integration/worklist.py", "source_location": "L499", "receiver": "active_findings"}, {"caller_nid": "integration_worklist_worklistprioritizer_score_single", "callee": "append", "is_member_call": true, "source_file": "/Users/nmiller/Documents/GitHub/aortica/aortica/integration/worklist.py", "source_location": "L512", "receiver": "active_findings"}, {"caller_nid": "integration_worklist_worklistprioritizer_score_single", "callee": "append", "is_member_call": true, "source_file": "/Users/nmiller/Documents/GitHub/aortica/aortica/integration/worklist.py", "source_location": "L525", "receiver": "active_findings"}, {"caller_nid": "integration_worklist_worklistprioritizer_score_single", "callee": "get", "is_member_call": true, "source_file": "/Users/nmiller/Documents/GitHub/aortica/aortica/integration/worklist.py", "source_location": "L533", "receiver": "predictions"}, {"caller_nid": "integration_worklist_worklistprioritizer_score_single", "callee": "items", "is_member_call": true, "source_file": "/Users/nmiller/Documents/GitHub/aortica/aortica/integration/worklist.py", "source_location": "L534", "receiver": "risk_preds"}, {"caller_nid": "integration_worklist_worklistprioritizer_score_single", "callee": "get", "is_member_call": true, "source_file": "/Users/nmiller/Documents/GitHub/aortica/aortica/integration/worklist.py", "source_location": "L535", "receiver": null}, {"caller_nid": "integration_worklist_worklistprioritizer_score_single", "callee": "get", "is_member_call": true, "source_file": "/Users/nmiller/Documents/GitHub/aortica/aortica/integration/worklist.py", "source_location": "L536", "receiver": "thresholds"}, {"caller_nid": "integration_worklist_worklistprioritizer_score_single", "callee": "get", "is_member_call": true, "source_file": "/Users/nmiller/Documents/GitHub/aortica/aortica/integration/worklist.py", "source_location": "L537", "receiver": "thresholds"}, {"caller_nid": "integration_worklist_worklistprioritizer_score_single", "callee": "get", "is_member_call": true, "source_file": "/Users/nmiller/Documents/GitHub/aortica/aortica/integration/worklist.py", "source_location": "L538", "receiver": "thresholds"}, {"caller_nid": "integration_worklist_worklistprioritizer_score_single", "callee": "append", "is_member_call": true, "source_file": "/Users/nmiller/Documents/GitHub/aortica/aortica/integration/worklist.py", "source_location": "L542", "receiver": "active_findings"}, {"caller_nid": "integration_worklist_worklistprioritizer_score_single", "callee": "append", "is_member_call": true, "source_file": "/Users/nmiller/Documents/GitHub/aortica/aortica/integration/worklist.py", "source_location": "L550", "receiver": "active_findings"}, {"caller_nid": "integration_worklist_worklistprioritizer_score_single", "callee": "append", "is_member_call": true, "source_file": "/Users/nmiller/Documents/GitHub/aortica/aortica/integration/worklist.py", "source_location": "L558", "receiver": "active_findings"}, {"caller_nid": "integration_worklist_worklistprioritizer_score_single", "callee": "sort", "is_member_call": true, "source_file": "/Users/nmiller/Documents/GitHub/aortica/aortica/integration/worklist.py", "source_location": "L576", "receiver": "active_findings"}, {"caller_nid": "integration_worklist_worklistprioritizer_score_single", "callee": "get", "is_member_call": true, "source_file": "/Users/nmiller/Documents/GitHub/aortica/aortica/integration/worklist.py", "source_location": "L578", "receiver": "tier_order"}, {"caller_nid": "integration_worklist_worklistprioritizer_prioritize", "callee": "ValueError", "is_member_call": false, "source_file": "/Users/nmiller/Documents/GitHub/aortica/aortica/integration/worklist.py", "source_location": "L656", "receiver": null}, {"caller_nid": "integration_worklist_worklistprioritizer_prioritize", "callee": "get", "is_member_call": true, "source_file": "/Users/nmiller/Documents/GitHub/aortica/aortica/integration/worklist.py", "source_location": "L679", "receiver": null}, {"caller_nid": "integration_worklist_worklistprioritizer_prioritize", "callee": "get", "is_member_call": true, "source_file": "/Users/nmiller/Documents/GitHub/aortica/aortica/integration/worklist.py", "source_location": "L681", "receiver": "_DEFAULT_ACTIONS"}, {"caller_nid": "integration_worklist_worklistprioritizer_prioritize", "callee": "append", "is_member_call": true, "source_file": "/Users/nmiller/Documents/GitHub/aortica/aortica/integration/worklist.py", "source_location": "L684", "receiver": "items"}, {"caller_nid": "integration_worklist_worklistprioritizer_prioritize", "callee": "sort", "is_member_call": true, "source_file": "/Users/nmiller/Documents/GitHub/aortica/aortica/integration/worklist.py", "source_location": "L695", "receiver": "items"}]}