{"nodes": [{"id": "users_nmiller_documents_github_aortica_aortica_reports_jsonld_report_py", "label": "jsonld_report.py", "file_type": "code", "source_file": "aortica/reports/jsonld_report.py", "source_location": "L1"}, {"id": "reports_jsonld_report_get_pyld", "label": "_get_pyld()", "file_type": "code", "source_file": "aortica/reports/jsonld_report.py", "source_location": "L42"}, {"id": "any", "label": "Any", "file_type": "code", "source_file": "", "source_location": ""}, {"id": "reports_jsonld_report_extract_predictions", "label": "_extract_predictions()", "file_type": "code", "source_file": "aortica/reports/jsonld_report.py", "source_location": "L200"}, {"id": "reports_jsonld_report_jsonldreport", "label": "JSONLDReport", "file_type": "code", "source_file": "aortica/reports/jsonld_report.py", "source_location": "L256"}, {"id": "reports_jsonld_report_build_finding_observation", "label": "_build_finding_observation()", "file_type": "code", "source_file": "aortica/reports/jsonld_report.py", "source_location": "L276"}, {"id": "reports_jsonld_report_build_risk_observation", "label": "_build_risk_observation()", "file_type": "code", "source_file": "aortica/reports/jsonld_report.py", "source_location": "L319"}, {"id": "reports_jsonld_report_validate_jsonld", "label": "_validate_jsonld()", "file_type": "code", "source_file": "aortica/reports/jsonld_report.py", "source_location": "L367"}, {"id": "reports_jsonld_report_generate_jsonld", "label": "generate_jsonld()", "file_type": "code", "source_file": "aortica/reports/jsonld_report.py", "source_location": "L401"}, {"id": "reports_jsonld_report_rationale_1", "label": "JSON-LD Machine-Readable Report Generator.  Generates a JSON-LD 1.1 document fro", "file_type": "rationale", "source_file": "aortica/reports/jsonld_report.py", "source_location": "L1"}, {"id": "reports_jsonld_report_rationale_203", "label": "Extract per-task prediction lists from various output formats.      Handles Mult", "file_type": "rationale", "source_file": "aortica/reports/jsonld_report.py", "source_location": "L203"}, {"id": "reports_jsonld_report_rationale_257", "label": "Container for a generated JSON-LD report.      Attributes:         document: The", "file_type": "rationale", "source_file": "aortica/reports/jsonld_report.py", "source_location": "L257"}, {"id": "reports_jsonld_report_rationale_282", "label": "Build a JSON-LD observation node for a single finding.      Args:         class_", "file_type": "rationale", "source_file": "aortica/reports/jsonld_report.py", "source_location": "L282"}, {"id": "reports_jsonld_report_rationale_324", "label": "Build a JSON-LD observation node for a risk prediction.      Args:         risk_", "file_type": "rationale", "source_file": "aortica/reports/jsonld_report.py", "source_location": "L324"}, {"id": "reports_jsonld_report_rationale_368", "label": "Validate JSON-LD via compaction/expansion round-trip.      Returns True if the d", "file_type": "rationale", "source_file": "aortica/reports/jsonld_report.py", "source_location": "L368"}, {"id": "reports_jsonld_report_rationale_410", "label": "Generate a JSON-LD machine-readable report from multi-task predictions.      Par", "file_type": "rationale", "source_file": "aortica/reports/jsonld_report.py", "source_location": "L410"}], "edges": [{"source": "users_nmiller_documents_github_aortica_aortica_reports_jsonld_report_py", "target": "hashlib", "relation": "imports", "context": "import", "confidence": "EXTRACTED", "source_file": "aortica/reports/jsonld_report.py", "source_location": "L25", "weight": 1.0}, {"source": "users_nmiller_documents_github_aortica_aortica_reports_jsonld_report_py", "target": "json", "relation": "imports", "context": "import", "confidence": "EXTRACTED", "source_file": "aortica/reports/jsonld_report.py", "source_location": "L26", "weight": 1.0}, {"source": "users_nmiller_documents_github_aortica_aortica_reports_jsonld_report_py", "target": "dataclasses", "relation": "imports_from", "context": "import", "confidence": "EXTRACTED", "source_file": "aortica/reports/jsonld_report.py", "source_location": "L27", "weight": 1.0}, {"source": "users_nmiller_documents_github_aortica_aortica_reports_jsonld_report_py", "target": "datetime", "relation": "imports_from", "context": "import", "confidence": "EXTRACTED", "source_file": "aortica/reports/jsonld_report.py", "source_location": "L28", "weight": 1.0}, {"source": "users_nmiller_documents_github_aortica_aortica_reports_jsonld_report_py", "target": "typing", "relation": "imports_from", "context": "import", "confidence": "EXTRACTED", "source_file": "aortica/reports/jsonld_report.py", "source_location": "L29", "weight": 1.0}, {"source": "users_nmiller_documents_github_aortica_aortica_reports_jsonld_report_py", "target": "aortica_models_ischaemia_head", "relation": "imports_from", "context": "import", "confidence": "EXTRACTED", "source_file": "aortica/reports/jsonld_report.py", "source_location": "L31", "weight": 1.0}, {"source": "users_nmiller_documents_github_aortica_aortica_reports_jsonld_report_py", "target": "aortica_models_rhythm_head", "relation": "imports_from", "context": "import", "confidence": "EXTRACTED", "source_file": "aortica/reports/jsonld_report.py", "source_location": "L32", "weight": 1.0}, {"source": "users_nmiller_documents_github_aortica_aortica_reports_jsonld_report_py", "target": "aortica_models_risk_head", "relation": "imports_from", "context": "import", "confidence": "EXTRACTED", "source_file": "aortica/reports/jsonld_report.py", "source_location": "L33", "weight": 1.0}, {"source": "users_nmiller_documents_github_aortica_aortica_reports_jsonld_report_py", "target": "aortica_models_structural_head", "relation": "imports_from", "context": "import", "confidence": "EXTRACTED", "source_file": "aortica/reports/jsonld_report.py", "source_location": "L34", "weight": 1.0}, {"source": "users_nmiller_documents_github_aortica_aortica_reports_jsonld_report_py", "target": "reports_jsonld_report_get_pyld", "relation": "contains", "confidence": "EXTRACTED", "source_file": "aortica/reports/jsonld_report.py", "source_location": "L42", "weight": 1.0}, {"source": "reports_jsonld_report_get_pyld", "target": "any", "relation": "references", "context": "return_type", "confidence": "EXTRACTED", "source_file": "aortica/reports/jsonld_report.py", "source_location": "L42", "weight": 1.0}, {"source": "users_nmiller_documents_github_aortica_aortica_reports_jsonld_report_py", "target": "reports_jsonld_report_extract_predictions", "relation": "contains", "confidence": "EXTRACTED", "source_file": "aortica/reports/jsonld_report.py", "source_location": "L200", "weight": 1.0}, {"source": "reports_jsonld_report_extract_predictions", "target": "any", "relation": "references", "context": "parameter_type", "confidence": "EXTRACTED", "source_file": "aortica/reports/jsonld_report.py", "source_location": "L200", "weight": 1.0}, {"source": "users_nmiller_documents_github_aortica_aortica_reports_jsonld_report_py", "target": "reports_jsonld_report_jsonldreport", "relation": "contains", "confidence": "EXTRACTED", "source_file": "aortica/reports/jsonld_report.py", "source_location": "L256", "weight": 1.0}, {"source": "users_nmiller_documents_github_aortica_aortica_reports_jsonld_report_py", "target": "reports_jsonld_report_build_finding_observation", "relation": "contains", "confidence": "EXTRACTED", "source_file": "aortica/reports/jsonld_report.py", "source_location": "L276", "weight": 1.0}, {"source": "reports_jsonld_report_build_finding_observation", "target": "any", "relation": "references", "context": "generic_arg", "confidence": "EXTRACTED", "source_file": "aortica/reports/jsonld_report.py", "source_location": "L276", "weight": 1.0}, {"source": "users_nmiller_documents_github_aortica_aortica_reports_jsonld_report_py", "target": "reports_jsonld_report_build_risk_observation", "relation": "contains", "confidence": "EXTRACTED", "source_file": "aortica/reports/jsonld_report.py", "source_location": "L319", "weight": 1.0}, {"source": "reports_jsonld_report_build_risk_observation", "target": "any", "relation": "references", "context": "generic_arg", "confidence": "EXTRACTED", "source_file": "aortica/reports/jsonld_report.py", "source_location": "L319", "weight": 1.0}, {"source": "users_nmiller_documents_github_aortica_aortica_reports_jsonld_report_py", "target": "reports_jsonld_report_validate_jsonld", "relation": "contains", "confidence": "EXTRACTED", "source_file": "aortica/reports/jsonld_report.py", "source_location": "L367", "weight": 1.0}, {"source": "reports_jsonld_report_validate_jsonld", "target": "any", "relation": "references", "context": "generic_arg", "confidence": "EXTRACTED", "source_file": "aortica/reports/jsonld_report.py", "source_location": "L367", "weight": 1.0}, {"source": "users_nmiller_documents_github_aortica_aortica_reports_jsonld_report_py", "target": "reports_jsonld_report_generate_jsonld", "relation": "contains", "confidence": "EXTRACTED", "source_file": "aortica/reports/jsonld_report.py", "source_location": "L401", "weight": 1.0}, {"source": "reports_jsonld_report_generate_jsonld", "target": "any", "relation": "references", "context": "parameter_type", "confidence": "EXTRACTED", "source_file": "aortica/reports/jsonld_report.py", "source_location": "L401", "weight": 1.0}, {"source": "reports_jsonld_report_generate_jsonld", "target": "any", "relation": "references", "context": "generic_arg", "confidence": "EXTRACTED", "source_file": "aortica/reports/jsonld_report.py", "source_location": "L401", "weight": 1.0}, {"source": "reports_jsonld_report_generate_jsonld", "target": "reports_jsonld_report_jsonldreport", "relation": "references", "context": "return_type", "confidence": "EXTRACTED", "source_file": "aortica/reports/jsonld_report.py", "source_location": "L401", "weight": 1.0}, {"source": "reports_jsonld_report_validate_jsonld", "target": "reports_jsonld_report_get_pyld", "relation": "calls", "context": "call", "confidence": "EXTRACTED", "source_file": "aortica/reports/jsonld_report.py", "source_location": "L373", "weight": 1.0}, {"source": "reports_jsonld_report_generate_jsonld", "target": "reports_jsonld_report_extract_predictions", "relation": "calls", "context": "call", "confidence": "EXTRACTED", "source_file": "aortica/reports/jsonld_report.py", "source_location": "L456", "weight": 1.0}, {"source": "reports_jsonld_report_generate_jsonld", "target": "reports_jsonld_report_build_finding_observation", "relation": "calls", "context": "call", "confidence": "EXTRACTED", "source_file": "aortica/reports/jsonld_report.py", "source_location": "L472", "weight": 1.0}, {"source": "reports_jsonld_report_generate_jsonld", "target": "reports_jsonld_report_build_risk_observation", "relation": "calls", "context": "call", "confidence": "EXTRACTED", "source_file": "aortica/reports/jsonld_report.py", "source_location": "L486", "weight": 1.0}, {"source": "reports_jsonld_report_generate_jsonld", "target": "reports_jsonld_report_validate_jsonld", "relation": "calls", "context": "call", "confidence": "EXTRACTED", "source_file": "aortica/reports/jsonld_report.py", "source_location": "L528", "weight": 1.0}, {"source": "reports_jsonld_report_generate_jsonld", "target": "reports_jsonld_report_jsonldreport", "relation": "calls", "context": "call", "confidence": "EXTRACTED", "source_file": "aortica/reports/jsonld_report.py", "source_location": "L530", "weight": 1.0}, {"source": "reports_jsonld_report_rationale_1", "target": "users_nmiller_documents_github_aortica_aortica_reports_jsonld_report_py", "relation": "rationale_for", "confidence": "EXTRACTED", "source_file": "aortica/reports/jsonld_report.py", "source_location": "L1", "weight": 1.0}, {"source": "reports_jsonld_report_rationale_203", "target": "reports_jsonld_report_extract_predictions", "relation": "rationale_for", "confidence": "EXTRACTED", "source_file": "aortica/reports/jsonld_report.py", "source_location": "L203", "weight": 1.0}, {"source": "reports_jsonld_report_rationale_257", "target": "reports_jsonld_report_jsonldreport", "relation": "rationale_for", "confidence": "EXTRACTED", "source_file": "aortica/reports/jsonld_report.py", "source_location": "L257", "weight": 1.0}, {"source": "reports_jsonld_report_rationale_282", "target": "reports_jsonld_report_build_finding_observation", "relation": "rationale_for", "confidence": "EXTRACTED", "source_file": "aortica/reports/jsonld_report.py", "source_location": "L282", "weight": 1.0}, {"source": "reports_jsonld_report_rationale_324", "target": "reports_jsonld_report_build_risk_observation", "relation": "rationale_for", "confidence": "EXTRACTED", "source_file": "aortica/reports/jsonld_report.py", "source_location": "L324", "weight": 1.0}, {"source": "reports_jsonld_report_rationale_368", "target": "reports_jsonld_report_validate_jsonld", "relation": "rationale_for", "confidence": "EXTRACTED", "source_file": "aortica/reports/jsonld_report.py", "source_location": "L368", "weight": 1.0}, {"source": "reports_jsonld_report_rationale_410", "target": "reports_jsonld_report_generate_jsonld", "relation": "rationale_for", "confidence": "EXTRACTED", "source_file": "aortica/reports/jsonld_report.py", "source_location": "L410", "weight": 1.0}], "raw_calls": [{"caller_nid": "reports_jsonld_report_get_pyld", "callee": "ImportError", "is_member_call": false, "source_file": "/Users/nmiller/Documents/GitHub/aortica/aortica/reports/jsonld_report.py", "source_location": "L49", "receiver": null}, {"caller_nid": "reports_jsonld_report_extract_predictions", "callee": "items", "is_member_call": true, "source_file": "/Users/nmiller/Documents/GitHub/aortica/aortica/reports/jsonld_report.py", "source_location": "L218", "receiver": "tasks"}, {"caller_nid": "reports_jsonld_report_extract_predictions", "callee": "get", "is_member_call": true, "source_file": "/Users/nmiller/Documents/GitHub/aortica/aortica/reports/jsonld_report.py", "source_location": "L223", "receiver": "multi_task_output"}, {"caller_nid": "reports_jsonld_report_extract_predictions", "callee": "numpy", "is_member_call": true, "source_file": "/Users/nmiller/Documents/GitHub/aortica/aortica/reports/jsonld_report.py", "source_location": "L232", "receiver": null}, {"caller_nid": "reports_jsonld_report_extract_predictions", "callee": "cpu", "is_member_call": true, "source_file": "/Users/nmiller/Documents/GitHub/aortica/aortica/reports/jsonld_report.py", "source_location": "L232", "receiver": null}, {"caller_nid": "reports_jsonld_report_extract_predictions", "callee": "detach", "is_member_call": true, "source_file": "/Users/nmiller/Documents/GitHub/aortica/aortica/reports/jsonld_report.py", "source_location": "L232", "receiver": "values"}, {"caller_nid": "reports_jsonld_report_extract_predictions", "callee": "tolist", "is_member_call": true, "source_file": "/Users/nmiller/Documents/GitHub/aortica/aortica/reports/jsonld_report.py", "source_location": "L234", "receiver": "values"}, {"caller_nid": "reports_jsonld_report_extract_predictions", "callee": "tolist", "is_member_call": true, "source_file": "/Users/nmiller/Documents/GitHub/aortica/aortica/reports/jsonld_report.py", "source_location": "L236", "receiver": "values"}, {"caller_nid": "reports_jsonld_report_build_finding_observation", "callee": "title", "is_member_call": true, "source_file": "/Users/nmiller/Documents/GitHub/aortica/aortica/reports/jsonld_report.py", "source_location": "L293", "receiver": null}, {"caller_nid": "reports_jsonld_report_build_finding_observation", "callee": "replace", "is_member_call": true, "source_file": "/Users/nmiller/Documents/GitHub/aortica/aortica/reports/jsonld_report.py", "source_location": "L293", "receiver": "class_name"}, {"caller_nid": "reports_jsonld_report_build_risk_observation", "callee": "get", "is_member_call": true, "source_file": "/Users/nmiller/Documents/GitHub/aortica/aortica/reports/jsonld_report.py", "source_location": "L334", "receiver": "_RISK_DISPLAY_NAMES"}, {"caller_nid": "reports_jsonld_report_build_risk_observation", "callee": "title", "is_member_call": true, "source_file": "/Users/nmiller/Documents/GitHub/aortica/aortica/reports/jsonld_report.py", "source_location": "L335", "receiver": null}, {"caller_nid": "reports_jsonld_report_build_risk_observation", "callee": "replace", "is_member_call": true, "source_file": "/Users/nmiller/Documents/GitHub/aortica/aortica/reports/jsonld_report.py", "source_location": "L335", "receiver": "risk_name"}, {"caller_nid": "reports_jsonld_report_validate_jsonld", "callee": "expand", "is_member_call": true, "source_file": "/Users/nmiller/Documents/GitHub/aortica/aortica/reports/jsonld_report.py", "source_location": "L378", "receiver": "jsonld"}, {"caller_nid": "reports_jsonld_report_validate_jsonld", "callee": "get", "is_member_call": true, "source_file": "/Users/nmiller/Documents/GitHub/aortica/aortica/reports/jsonld_report.py", "source_location": "L384", "receiver": "document"}, {"caller_nid": "reports_jsonld_report_validate_jsonld", "callee": "compact", "is_member_call": true, "source_file": "/Users/nmiller/Documents/GitHub/aortica/aortica/reports/jsonld_report.py", "source_location": "L385", "receiver": "jsonld"}, {"caller_nid": "reports_jsonld_report_generate_jsonld", "callee": "isoformat", "is_member_call": true, "source_file": "/Users/nmiller/Documents/GitHub/aortica/aortica/reports/jsonld_report.py", "source_location": "L440", "receiver": null}, {"caller_nid": "reports_jsonld_report_generate_jsonld", "callee": "now", "is_member_call": true, "source_file": "/Users/nmiller/Documents/GitHub/aortica/aortica/reports/jsonld_report.py", "source_location": "L440", "receiver": "datetime"}, {"caller_nid": "reports_jsonld_report_generate_jsonld", "callee": "get", "is_member_call": true, "source_file": "/Users/nmiller/Documents/GitHub/aortica/aortica/reports/jsonld_report.py", "source_location": "L441", "receiver": "ecg_metadata"}, {"caller_nid": "reports_jsonld_report_generate_jsonld", "callee": "get", "is_member_call": true, "source_file": "/Users/nmiller/Documents/GitHub/aortica/aortica/reports/jsonld_report.py", "source_location": "L445", "receiver": "ecg_metadata"}, {"caller_nid": "reports_jsonld_report_generate_jsonld", "callee": "hexdigest", "is_member_call": true, "source_file": "/Users/nmiller/Documents/GitHub/aortica/aortica/reports/jsonld_report.py", "source_location": "L449", "receiver": null}, {"caller_nid": "reports_jsonld_report_generate_jsonld", "callee": "sha256", "is_member_call": true, "source_file": "/Users/nmiller/Documents/GitHub/aortica/aortica/reports/jsonld_report.py", "source_location": "L449", "receiver": "hashlib"}, {"caller_nid": "reports_jsonld_report_generate_jsonld", "callee": "read", "is_member_call": true, "source_file": "/Users/nmiller/Documents/GitHub/aortica/aortica/reports/jsonld_report.py", "source_location": "L449", "receiver": "f"}, {"caller_nid": "reports_jsonld_report_generate_jsonld", "callee": "items", "is_member_call": true, "source_file": "/Users/nmiller/Documents/GitHub/aortica/aortica/reports/jsonld_report.py", "source_location": "L466", "receiver": "classification_tasks"}, {"caller_nid": "reports_jsonld_report_generate_jsonld", "callee": "get", "is_member_call": true, "source_file": "/Users/nmiller/Documents/GitHub/aortica/aortica/reports/jsonld_report.py", "source_location": "L467", "receiver": "predictions"}, {"caller_nid": "reports_jsonld_report_generate_jsonld", "callee": "get", "is_member_call": true, "source_file": "/Users/nmiller/Documents/GitHub/aortica/aortica/reports/jsonld_report.py", "source_location": "L471", "receiver": "confidence_intervals"}, {"caller_nid": "reports_jsonld_report_generate_jsonld", "callee": "append", "is_member_call": true, "source_file": "/Users/nmiller/Documents/GitHub/aortica/aortica/reports/jsonld_report.py", "source_location": "L478", "receiver": "observations"}, {"caller_nid": "reports_jsonld_report_generate_jsonld", "callee": "get", "is_member_call": true, "source_file": "/Users/nmiller/Documents/GitHub/aortica/aortica/reports/jsonld_report.py", "source_location": "L481", "receiver": "predictions"}, {"caller_nid": "reports_jsonld_report_generate_jsonld", "callee": "get", "is_member_call": true, "source_file": "/Users/nmiller/Documents/GitHub/aortica/aortica/reports/jsonld_report.py", "source_location": "L485", "receiver": "confidence_intervals"}, {"caller_nid": "reports_jsonld_report_generate_jsonld", "callee": "append", "is_member_call": true, "source_file": "/Users/nmiller/Documents/GitHub/aortica/aortica/reports/jsonld_report.py", "source_location": "L491", "receiver": "observations"}, {"caller_nid": "reports_jsonld_report_generate_jsonld", "callee": "get", "is_member_call": true, "source_file": "/Users/nmiller/Documents/GitHub/aortica/aortica/reports/jsonld_report.py", "source_location": "L503", "receiver": "ecg_metadata"}, {"caller_nid": "reports_jsonld_report_generate_jsonld", "callee": "dumps", "is_member_call": true, "source_file": "/Users/nmiller/Documents/GitHub/aortica/aortica/reports/jsonld_report.py", "source_location": "L525", "receiver": "json"}]}